structured_logprobs/__init__.py
structured_logprobs/helpers.py
structured_logprobs/main.py
structured_logprobs-0.1.5.dist-info/LICENSE
structured_logprobs-0.1.5.dist-info/METADATA
structured_logprobs-0.1.5.dist-info/WHEEL
structured_logprobs-0.1.5.dist-info/top_level.txt
structured_logprobs-0.1.5.dist-info/RECORD
