Metadata-Version: 2.2
Name: structured-logprobs
Version: 0.1.5
Summary: Logprobs for OpenAI Structured Outputs
Author-email: Sarus Technologies <nicolas.grislain@gmail.com>
Project-URL: Homepage, https://arena-ai.github.io/structured-logprobs/
Project-URL: Repository, https://github.com/arena-ai/structured-logprobs
Project-URL: Documentation, https://arena-ai.github.io/structured-logprobs/
Keywords: python
Classifier: Intended Audience :: Developers
Classifier: Programming Language :: Python
Classifier: Programming Language :: Python :: 3
Classifier: Programming Language :: Python :: 3.9
Classifier: Programming Language :: Python :: 3.10
Classifier: Programming Language :: Python :: 3.11
Classifier: Programming Language :: Python :: 3.12
Classifier: Programming Language :: Python :: 3.13
Classifier: Topic :: Software Development :: Libraries :: Python Modules
Requires-Python: <4.0,>=3.10
License-File: LICENSE
Requires-Dist: openai~=1.58.1
Requires-Dist: pydantic~=2.10.4
Requires-Dist: lark~=1.2.2
